agentex/__init__.py
agentex/_base_client.py
agentex/_client.py
agentex/_compat.py
agentex/_constants.py
agentex/_exceptions.py
agentex/_files.py
agentex/_models.py
agentex/_qs.py
agentex/_resource.py
agentex/_response.py
agentex/_streaming.py
agentex/_types.py
agentex/_version.py
agentex/py.typed
agentex/_utils/__init__.py
agentex/_utils/_compat.py
agentex/_utils/_datetime_parse.py
agentex/_utils/_logs.py
agentex/_utils/_proxy.py
agentex/_utils/_reflection.py
agentex/_utils/_resources_proxy.py
agentex/_utils/_streams.py
agentex/_utils/_sync.py
agentex/_utils/_transform.py
agentex/_utils/_typing.py
agentex/_utils/_utils.py
agentex/lib/.keep
agentex/lib/__init__.py
agentex/lib/environment_variables.py
agentex/lib/py.typed
agentex/lib/adk/__init__.py
agentex/lib/adk/_modules/__init__.py
agentex/lib/adk/_modules/acp.py
agentex/lib/adk/_modules/agent_task_tracker.py
agentex/lib/adk/_modules/agents.py
agentex/lib/adk/_modules/events.py
agentex/lib/adk/_modules/messages.py
agentex/lib/adk/_modules/state.py
agentex/lib/adk/_modules/streaming.py
agentex/lib/adk/_modules/tasks.py
agentex/lib/adk/_modules/tracing.py
agentex/lib/adk/providers/__init__.py
agentex/lib/adk/providers/_modules/__init__.py
agentex/lib/adk/providers/_modules/litellm.py
agentex/lib/adk/providers/_modules/openai.py
agentex/lib/adk/providers/_modules/sgp.py
agentex/lib/adk/providers/_modules/sync_provider.py
agentex/lib/adk/utils/__init__.py
agentex/lib/adk/utils/_modules/__init__.py
agentex/lib/adk/utils/_modules/client.py
agentex/lib/adk/utils/_modules/templating.py
agentex/lib/cli/__init__.py
agentex/lib/cli/commands/__init__.py
agentex/lib/cli/commands/agents.py
agentex/lib/cli/commands/init.py
agentex/lib/cli/commands/main.py
agentex/lib/cli/commands/secrets.py
agentex/lib/cli/commands/tasks.py
agentex/lib/cli/commands/uv.py
agentex/lib/cli/debug/__init__.py
agentex/lib/cli/debug/debug_config.py
agentex/lib/cli/debug/debug_handlers.py
agentex/lib/cli/handlers/__init__.py
agentex_sdk-0.9.1.dist-info/METADATA
agentex_sdk-0.9.1.dist-info/WHEEL
agentex_sdk-0.9.1.dist-info/entry_points.txt
agentex_sdk-0.9.1.dist-info/licenses/LICENSE
agentex_sdk-0.9.1.dist-info/RECORD
