Metadata-Version: 2.3
Name: agentex-sdk
Version: 0.9.1
Summary: The official Python library for the agentex API
Project-URL: Homepage, https://github.com/scaleapi/scale-agentex-python
Project-URL: Repository, https://github.com/scaleapi/scale-agentex-python
Author-email: Agentex <roxanne.farhad@scale.com>
License: Apache-2.0
Classifier: Intended Audience :: Developers
Classifier: License :: OSI Approved :: Apache Software License
Classifier: Operating System :: MacOS
Classifier: Operating System :: Microsoft :: Windows
Classifier: Operating System :: OS Independent
Classifier: Operating System :: POSIX
Classifier: Operating System :: POSIX :: Linux
Classifier: Programming Language :: Python :: 3.12
Classifier: Programming Language :: Python :: 3.13
Classifier: Programming Language :: Python :: 3.14
Classifier: Topic :: Software Development :: Libraries :: Python Modules
Classifier: Typing :: Typed
Requires-Python: <4,>=3.12
Requires-Dist: aiohttp<4,>=3.10.10
Requires-Dist: anthropic>=0.40.0
Requires-Dist: anyio<5,>=3.5.0
Requires-Dist: claude-agent-sdk>=0.1.0
Requires-Dist: cloudpickle>=3.1.1
Requires-Dist: datadog>=0.52.1
Requires-Dist: ddtrace>=3.13.0
Requires-Dist: distro<2,>=1.7.0
Requires-Dist: fastapi<0.116,>=0.115.0
Requires-Dist: httpx<0.28,>=0.27.2
Requires-Dist: ipykernel>=6.29.5
Requires-Dist: jinja2<4,>=3.1.3
Requires-Dist: json-log-formatter>=1.1.1
Requires-Dist: jsonref<2,>=1.1.0
Requires-Dist: jsonschema<5,>=4.23.0
Requires-Dist: kubernetes<29.0.0,>=25.0.0
Requires-Dist: litellm<2,>=1.66.0
Requires-Dist: mcp[cli]>=1.4.1
Requires-Dist: openai-agents==0.4.2
Requires-Dist: openai<3,>=2.2
Requires-Dist: pydantic<3,>=2.0.0
Requires-Dist: pytest-asyncio>=1.0.0
Requires-Dist: pytest>=8.4.0
Requires-Dist: python-on-whales<0.74,>=0.73.0
Requires-Dist: pyyaml<7,>=6.0.2
Requires-Dist: questionary<3,>=2.0.1
Requires-Dist: redis<6,>=5.2.0
Requires-Dist: rich<14,>=13.9.2
Requires-Dist: scale-gp-beta>=0.1.0a20
Requires-Dist: scale-gp>=0.1.0a59
Requires-Dist: sniffio
Requires-Dist: temporalio<2,>=1.18.2
Requires-Dist: typer<0.17,>=0.16
Requires-Dist: typing-extensions<5,>=4.10
Requires-Dist: tzdata>=2025.2
Requires-Dist: tzlocal>=5.3.1
Requires-Dist: uvicorn>=0.31.1
Requires-Dist: watchfiles<1.0,>=0.24.0
Requires-Dist: yaspin>=3.1.0
Provides-Extra: aiohttp
Requires-Dist: aiohttp; extra == 'aiohttp'
Requires-Dist: httpx-aiohttp>=0.1.9; extra == 'aiohttp'
Provides-Extra: dev
Requires-Dist: ruff>=0.3.4; extra == 'dev'
